tokendito/__init__.py
tokendito/__main__.py
tokendito/aws.py
tokendito/config.py
tokendito/duo.py
tokendito/http_client.py
tokendito/okta.py
tokendito/tokendito.py
tokendito/user.py
tokendito-2.4.2.dist-info/AUTHORS.md
tokendito-2.4.2.dist-info/LICENSE.txt
tokendito-2.4.2.dist-info/METADATA
tokendito-2.4.2.dist-info/WHEEL
tokendito-2.4.2.dist-info/entry_points.txt
tokendito-2.4.2.dist-info/top_level.txt
tokendito-2.4.2.dist-info/RECORD
