Metadata-Version: 2.2
Name: tokendito
Version: 2.4.2
Summary: Get AWS STS tokens from Okta SSO
Home-page: https://github.com/dowjones/tokendito
Author: tokendito
Author-email: tokendito@dowjones.com
License: Apache 2.0
Keywords: okta,aws,sts
Classifier: License :: OSI Approved :: Apache Software License
Classifier: Development Status :: 5 - Production/Stable
Classifier: Operating System :: OS Independent
Classifier: Environment :: Console
Classifier: Programming Language :: Python
Classifier: Intended Audience :: End Users/Desktop
Classifier: Intended Audience :: Developers
Classifier: Intended Audience :: System Administrators
Classifier: Programming Language :: Python :: 3.9
Classifier: Programming Language :: Python :: 3.10
Classifier: Programming Language :: Python :: 3.11
Requires-Python: >=3.9
License-File: LICENSE.txt
License-File: AUTHORS.md
Requires-Dist: beautifulsoup4>=4.6.0
Requires-Dist: botocore>=1.12.36
Requires-Dist: certifi>=2022.12.07
Requires-Dist: platformdirs>=2.5.4
Requires-Dist: requests>=2.19.0
Dynamic: author
Dynamic: author-email
Dynamic: classifier
Dynamic: description
Dynamic: description-content-type
Dynamic: home-page
Dynamic: keywords
Dynamic: license
Dynamic: requires-dist
Dynamic: requires-python
Dynamic: summary
